kirlent_sphinx/__init__.py
kirlent_sphinx/slides.py
kirlent_sphinx/tables.py
kirlent_sphinx/templates/kirlent_impressjs/layout.html
kirlent_sphinx/templates/kirlent_impressjs/static/css/classic-slides.css
kirlent_sphinx/templates/kirlent_impressjs/static/css/kirlent.css_t
kirlent_sphinx/templates/kirlent_impressjs/static/css/tailwind.min.css
kirlent_sphinx/templates/kirlent_impressjs/static/js/impress.js
kirlent_sphinx/templates/kirlent_impressjs/theme.conf
kirlent_sphinx/templates/kirlent_revealjs/layout.html
kirlent_sphinx/templates/kirlent_revealjs/static/LICENSE
kirlent_sphinx/templates/kirlent_revealjs/static/css/kirlent.css_t
kirlent_sphinx/templates/kirlent_revealjs/static/css/print/paper.css
kirlent_sphinx/templates/kirlent_revealjs/static/css/print/pdf.css
kirlent_sphinx/templates/kirlent_revealjs/static/css/reveal.css
kirlent_sphinx/templates/kirlent_revealjs/static/css/reveal.css.orig
kirlent_sphinx/templates/kirlent_revealjs/static/css/tailwind.min.css
kirlent_sphinx/templates/kirlent_revealjs/static/js/reveal.js
kirlent_sphinx/templates/kirlent_revealjs/static/lib/js/classList.js
kirlent_sphinx/templates/kirlent_revealjs/static/lib/js/head.min.js
kirlent_sphinx/templates/kirlent_revealjs/static/plugin/multiplex/client.js
kirlent_sphinx/templates/kirlent_revealjs/static/plugin/multiplex/index.js
kirlent_sphinx/templates/kirlent_revealjs/static/plugin/multiplex/master.js
kirlent_sphinx/templates/kirlent_revealjs/static/plugin/notes/notes.html
kirlent_sphinx/templates/kirlent_revealjs/static/plugin/notes/notes.js
kirlent_sphinx/templates/kirlent_revealjs/static/plugin/notes-server/client.js
kirlent_sphinx/templates/kirlent_revealjs/static/plugin/notes-server/index.js
kirlent_sphinx/templates/kirlent_revealjs/static/plugin/notes-server/notes.html
kirlent_sphinx/templates/kirlent_revealjs/static/plugin/zoom-js/zoom.js
kirlent_sphinx/templates/kirlent_revealjs/theme.conf
kirlent_sphinx/templates/styles/base.css
kirlent_sphinx/templates/styles/impressjs.css
kirlent_sphinx-0.3.0.dist-info/LICENSE.tailwind.txt
kirlent_sphinx-0.3.0.dist-info/LICENSE.txt
kirlent_sphinx-0.3.0.dist-info/LICENSE_cloud_sptheme.txt
kirlent_sphinx-0.3.0.dist-info/LICENSE_impressjs.txt
kirlent_sphinx-0.3.0.dist-info/LICENSE_revealjs.txt
kirlent_sphinx-0.3.0.dist-info/LICENSE_sphinxjp.themes.revealjs.txt
kirlent_sphinx-0.3.0.dist-info/WHEEL
kirlent_sphinx-0.3.0.dist-info/METADATA
kirlent_sphinx-0.3.0.dist-info/RECORD
