Metadata-Version: 2.1
Name: kirlent-sphinx
Version: 0.3.0
Summary: Sphinx extension for slides and extended tables.
Home-page: https://gitlab.com/tekir/kirlent_sphinx
License: BSD-3-Clause
Keywords: sphinx,table,slide,presentation
Author: H. Turgut Uyar
Author-email: uyar@tekir.org
Requires-Python: >=3.5,<4.0
Classifier: Development Status :: 4 - Beta
Classifier: Environment :: Console
Classifier: Framework :: Sphinx :: Extension
Classifier: Intended Audience :: Education
Classifier: Intended Audience :: End Users/Desktop
Classifier: License :: OSI Approved :: BSD License
Classifier: Operating System :: OS Independent
Classifier: Programming Language :: Python :: 3
Classifier: Programming Language :: Python :: 3.5
Classifier: Programming Language :: Python :: 3.6
Classifier: Programming Language :: Python :: 3.7
Classifier: Programming Language :: Python :: Implementation :: CPython
Classifier: Programming Language :: Python :: Implementation :: PyPy
Classifier: Topic :: Text Processing :: Markup :: HTML
Requires-Dist: sphinx (>=1.8,<2.0)
Project-URL: Documentation, https://gitlab.com/tekir/kirlent_sphinx
Project-URL: Repository, https://gitlab.com/tekir/kirlent_sphinx
